pipen_dry.py
pipen_dry-1.1.0.dist-info/METADATA
pipen_dry-1.1.0.dist-info/WHEEL
pipen_dry-1.1.0.dist-info/entry_points.txt
pipen_dry-1.1.0.dist-info/RECORD
